progressive/__init__.py
progressive/bar.py
progressive/cursor.py
progressive/examples.py
progressive/exceptions.py
progressive/pretty.py
progressive/tree.py
progressive/util.py
progressive-0.3.4.dist-info/DESCRIPTION.rst
progressive-0.3.4.dist-info/METADATA
progressive-0.3.4.dist-info/RECORD
progressive-0.3.4.dist-info/WHEEL
progressive-0.3.4.dist-info/metadata.json
progressive-0.3.4.dist-info/pbr.json
progressive-0.3.4.dist-info/top_level.txt
